LICENSE
MANIFEST.in
README.md
requirements.txt
setup.py
btgsolutions_tradeservices/__init__.py
btgsolutions_tradeservices/rest/__init__.py
btgsolutions_tradeservices/rest/btgSolutionsTradeServiceExample.py
btgsolutions_tradeservices/rest/order_controller.py
btgsolutions_tradeservices_python_client.egg-info/PKG-INFO
btgsolutions_tradeservices_python_client.egg-info/SOURCES.txt
btgsolutions_tradeservices_python_client.egg-info/dependency_links.txt
btgsolutions_tradeservices_python_client.egg-info/requires.txt
btgsolutions_tradeservices_python_client.egg-info/top_level.txt