Metadata-Version: 2.1
Name: btgsolutions-tradeservices-python-client
Version: 0.1.13
Summary: Python client package for trading within BTG Solutions platform.
Home-page: https://github.com/BTG-Pactual-Solutions/btgsolutions-tradeservices-python-client
Author: BTG Pactual Solutions Trade API
Requires-Python: >=3.7
License-File: LICENSE
Requires-Dist: pandas==2.2.2
Requires-Dist: requests==2.32.3
